stl2obj.cp39-win_amd64.pyd
stl2obj-0.3.dist-info/LICENSE
stl2obj-0.3.dist-info/METADATA
stl2obj-0.3.dist-info/WHEEL
stl2obj-0.3.dist-info/top_level.txt
stl2obj-0.3.dist-info/RECORD
